hyprland_ipc/__about__.py
hyprland_ipc/__init__.py
hyprland_ipc/ipc.py
hyprland_ipc/py.typed
hyprland_ipc-0.1.0.dist-info/METADATA
hyprland_ipc-0.1.0.dist-info/WHEEL
hyprland_ipc-0.1.0.dist-info/licenses/LICENSE.txt
hyprland_ipc-0.1.0.dist-info/licenses/LICENSES/MIT.txt
hyprland_ipc-0.1.0.dist-info/RECORD
