Metadata-Version: 2.4
Name: hyprland-ipc
Version: 0.1.0
Summary: A modern, type-safe IPC client for Hyprland's UNIX sockets.
Project-URL: Documentation, https://github.com/peppapig450/hyprland-ipc#readme
Project-URL: Homepage, https://github.com/peppapig450/hyprland-ipc
Project-URL: Issues, https://github.com/peppapig450/hyprland-ipc/issues
Project-URL: Source, https://github.com/peppapig450/hyprland-ipc
Author-email: peppapig450 <peppapig450@pm.me>
License-Expression: MIT
License-File: LICENSE.txt
License-File: LICENSES/MIT.txt
Keywords: hyprland,ipc,socket,wayland
Classifier: Development Status :: 4 - Beta
Classifier: License :: OSI Approved :: MIT License
Classifier: Operating System :: POSIX :: Linux
Classifier: Programming Language :: Python
Classifier: Programming Language :: Python :: 3.12
Classifier: Programming Language :: Python :: 3.13
Classifier: Programming Language :: Python :: 3.14
Classifier: Programming Language :: Python :: Implementation :: CPython
Classifier: Programming Language :: Python :: Implementation :: PyPy
Classifier: Topic :: Desktop Environment
Classifier: Topic :: Desktop Environment :: Window Managers
Classifier: Topic :: Software Development :: Libraries :: Python Modules
Classifier: Typing :: Typed
Requires-Python: >=3.12
